beprepared/__init__.py
beprepared/cli.py
beprepared/dataset.py
beprepared/external/SwinIR_wrapper/SwinIR.py
beprepared/external/SwinIR_wrapper/__init__.py
beprepared/external/SwinIR_wrapper/network_swinir.py
beprepared/external/__init__.py
beprepared/image.py
beprepared/llm.py
beprepared/logging.py
beprepared/node.py
beprepared/nodes/__init__.py
beprepared/nodes/aesthetics.py
beprepared/nodes/clip.py
beprepared/nodes/convert_format.py
beprepared/nodes/dedupe.py
beprepared/nodes/downscale.py
beprepared/nodes/filters.py
beprepared/nodes/florence2caption.py
beprepared/nodes/geminicaption.py
beprepared/nodes/gpt4ocaption.py
beprepared/nodes/humanfilter.py
beprepared/nodes/humantag.py
beprepared/nodes/joycaptionalpha1.py
beprepared/nodes/joycaptionalpha2.py
beprepared/nodes/llamacaption.py
beprepared/nodes/llmtransform.py
beprepared/nodes/load.py
beprepared/nodes/molmocaption.py
beprepared/nodes/nudenet.py
beprepared/nodes/qwenvlcaption.py
beprepared/nodes/save.py
beprepared/nodes/tags.py
beprepared/nodes/upscale.py
beprepared/nodes/utils.py
beprepared/nodes/xgenmmcaption.py
beprepared/properties.py
beprepared/utils.py
beprepared/web/.gitignore
beprepared/web/.vscode/extensions.json
beprepared/web/App.vue
beprepared/web/Generic.vue
beprepared/web/HumanFilter.vue
beprepared/web/HumanTag.vue
beprepared/web/index.html
beprepared/web/main.js
beprepared/web/package-lock.json
beprepared/web/package.json
beprepared/web/public/beprepared.jpg
beprepared/web/static/assets/index.bed43177.css
beprepared/web/static/assets/index.cccdb8a9.js
beprepared/web/static/beprepared.jpg
beprepared/web/static/index.html
beprepared/web/vite.config.js
beprepared/web.py
beprepared/workspace.py
beprepared-0.2.2.dist-info/LICENSE
beprepared-0.2.2.dist-info/METADATA
beprepared-0.2.2.dist-info/WHEEL
beprepared-0.2.2.dist-info/entry_points.txt
beprepared-0.2.2.dist-info/RECORD
