Metadata-Version: 2.1
Name: beprepared
Version: 0.2.2
Summary: 
License: GPL-3.0-only
Author: Brian Luczkiewicz
Author-email: brian@blucz.com
Requires-Python: >=3.10,<3.13
Classifier: License :: OSI Approved :: GNU General Public License v3 (GPLv3)
Classifier: Programming Language :: Python :: 3
Classifier: Programming Language :: Python :: 3.10
Classifier: Programming Language :: Python :: 3.11
Classifier: Programming Language :: Python :: 3.12
Requires-Dist: annoy (>=1.17.3,<2.0.0)
Requires-Dist: bitsandbytes (>=0.45.0,<0.46.0)
Requires-Dist: colorama (>=0.4.6,<0.5.0)
Requires-Dist: colorlog (>=6.9.0,<7.0.0)
Requires-Dist: einops (>=0.8.0,<0.9.0)
Requires-Dist: einops-exts (>=0.0.4,<0.0.5)
Requires-Dist: fastapi (>=0.115.0,<0.116.0)
Requires-Dist: google-generativeai (>=0.8.3,<0.9.0)
Requires-Dist: litellm (>=1.48.3,<2.0.0)
Requires-Dist: nudenet (>=3.4.2)
Requires-Dist: numba (>=0.60.0,<0.61.0)
Requires-Dist: open-clip-torch (>=2.26.1,<3.0.0)
Requires-Dist: openai (>=1.48.0,<2.0.0)
Requires-Dist: opencv-python (>=4.10.0.84,<5.0.0.0)
Requires-Dist: peft (>=0.12.0,<0.13.0)
Requires-Dist: pydantic (>=2.9.2,<3.0.0)
Requires-Dist: qwen-vl-utils (>=0.0.8,<0.0.9)
Requires-Dist: realesrgan (>=0.3.0,<0.4.0)
Requires-Dist: scikit-learn (>=1.5.2,<2.0.0)
Requires-Dist: sentencepiece (>=0.2.0,<0.3.0)
Requires-Dist: simple-aesthetics-predictor (>=0.1.2,<0.2.0)
Requires-Dist: tomli (>=2.0.1,<3.0.0)
Requires-Dist: torch (>=2.4.1,<3.0.0)
Requires-Dist: torchvision (>=0.19.1,<0.20.0)
Requires-Dist: tqdm (>=4.66.5,<5.0.0)
Requires-Dist: uvicorn[standard] (>=0.32.1,<0.33.0)
